colda/StopRequest.py
colda/__init__.py
colda/__version__.py
colda/_typing.py
colda/api.py
colda/algorithm/__init__.py
colda/algorithm/api.py
colda/algorithm/base.py
colda/algorithm/utils.py
colda/algorithm/common_stage/__init__.py
colda/algorithm/common_stage/api.py
colda/algorithm/common_stage/make_dataset.py
colda/algorithm/common_stage/make_hash.py
colda/algorithm/common_stage/make_match_idx.py
colda/algorithm/metric/__init__.py
colda/algorithm/metric/api.py
colda/algorithm/metric/base.py
colda/algorithm/metric/metrics.py
colda/algorithm/model/__init__.py
colda/algorithm/model/api.py
colda/algorithm/model/base.py
colda/algorithm/model/models.py
colda/algorithm/model/models_prev.py
colda/algorithm/model/my_model.py
colda/algorithm/strategy/__init__.py
colda/algorithm/strategy/abstract_algorithm_strategy.py
colda/algorithm/strategy/api.py
colda/algorithm/strategy/base.py
colda/algorithm/strategy/dp.py
colda/algorithm/strategy/test_algorithm.py
colda/algorithm/strategy/train_algorithm.py
colda/algorithm/strategy/utils.py
colda/algorithm/strategy/custom/__init__.py
colda/algorithm/strategy/custom/api.py
colda/algorithm/strategy/custom/custom_factory.py
colda/algorithm/strategy/custom/test_custom.py
colda/algorithm/strategy/custom/train_custom.py
colda/algorithm/test_stage/__init__.py
colda/algorithm/test_stage/api.py
colda/algorithm/test_stage/make_eval.py
colda/algorithm/test_stage/make_test.py
colda/algorithm/test_stage/make_test_local.py
colda/algorithm/train_stage/__init__.py
colda/algorithm/train_stage/api.py
colda/algorithm/train_stage/make_residual.py
colda/algorithm/train_stage/make_result.py
colda/algorithm/train_stage/make_train.py
colda/algorithm/train_stage/make_train_local.py
colda/authentication/__init__.py
colda/authentication/api.py
colda/authentication/authentication.py
colda/authentication/base.py
colda/authentication/logout.py
colda/authentication/utils.py
colda/database/__init__.py
colda/database/abstract_database.py
colda/database/api.py
colda-0.0.1.dist-info/LICENSE
colda-0.0.1.dist-info/METADATA
colda-0.0.1.dist-info/WHEEL
colda-0.0.1.dist-info/top_level.txt
colda-0.0.1.dist-info/RECORD
