Metadata-Version: 2.1
Name: colda
Version: 0.0.1
Summary: Collaborative Data Analysis for All
Home-page: https://github.com/Collaborative-AI/colda
Author: ColAI
Author-email: diaoenmao@gmail.com
License: Apache 2.0
Keywords: colda,collaborative data analysis,data science,machine learning
Classifier: Development Status :: 5 - Production/Stable
Classifier: Intended Audience :: Developers
Classifier: License :: OSI Approved :: Apache Software License
Classifier: Programming Language :: Python :: 3
Requires-Python: >=3.7
License-File: LICENSE
Requires-Dist: numpy (>=1.20.3)
Requires-Dist: pandas (>=1.3.4)
Requires-Dist: parso (>=0.8.2)
Requires-Dist: pytest (>=6.2.4)
Requires-Dist: requests (>=2.26.0)
Requires-Dist: scikit-learn (>=0.24.2)
Requires-Dist: scipy (>=1.7.1)
Requires-Dist: torch (>=1.11.0)
